{
    "objects": [
        {
            "name": "name",
            "datatype": "string",
            "claims": [
                {
                    "sourceId": "source1",
                    "fact": "Tina Grdner Montgomdry Chase"
                },
                {
                    "sourceId": "source2",
                    "fact": "Tonya Munoz Marsh Smith"
                },
                {
                    "sourceId": "source3",
                    "fact": "Tina Charles Montgomery Chase"
                },
                {
                    "sourceId": "source4",
                    "fact": "Tina Gardner Montxomcry Chasz"
                },
                {
                    "sourceId": "source5",
                    "fact": "Tina Gardnec Montgomury ChaIe"
                },
                {
                    "sourceId": "source6",
                    "fact": "Tiaa Gardnjr ontgomery Chase"
                },
                {
                    "sourceId": "source7",
                    "fact": "Nicole Rhodes Young Gibson"
                },
                {
                    "sourceId": "source8",
                    "fact": "oina Gardner Montgomery ChaCe"
                },
                {
                    "sourceId": "source9",
                    "fact": "Danny Chapman Hicks Parks"
                },
                {
                    "sourceId": "source10",
                    "fact": "Tina GardneC Motgoeery Chase"
                },
                {
                    "sourceId": "source11",
                    "fact": "Dustin Gardner Montgomery Chase"
                },
                {
                    "sourceId": "source12",
                    "fact": "Tina Adam Montgomery Chase"
                },
                {
                    "sourceId": "source13",
                    "fact": "Emily Gardner Montgomery Chase"
                },
                {
                    "sourceId": "source14",
                    "fact": "Jessica Gardner Montgomery Chase"
                },
                {
                    "sourceId": "source15",
                    "fact": "Roger Scott Clark"
                },
                {
                    "sourceId": "source16",
                    "fact": "Tina Gardner Montgomery Charles"
                },
                {
                    "sourceId": "source17",
                    "fact": "Tina Gardner Montgomery Chase"
                },
                {
                    "sourceId": "source18",
                    "fact": "Tina Gardner Montgomery Chase"
                },
                {
                    "sourceId": "source19",
                    "fact": "Tina Gardner Montgomery Chase"
                },
                {
                    "sourceId": "source20",
                    "fact": "Tina Gardner Montgomery Chase"
                }
            ],
            "truth": "Tina Gardner Montgomery Chase"
        }
    ],
    "sources": []
}