{
    "objects": [
        {
            "name": "nationality",
            "datatype": "categorical",
            "truth": "Azerbaijan",
            "claims": [
                {
                    "sourceId": "source1",
                    "fact": "Mauritania"
                },
                {
                    "sourceId": "source2",
                    "fact": "Isle of Man"
                },
                {
                    "sourceId": "source3",
                    "fact": "Slovakia (Slovak Republic)"
                },
                {
                    "sourceId": "source4",
                    "fact": "Sudan"
                },
                {
                    "sourceId": "source5",
                    "fact": "South Africa"
                },
                {
                    "sourceId": "source6",
                    "fact": "Comoros"
                },
                {
                    "sourceId": "source7",
                    "fact": "Cote d'Ivoire"
                },
                {
                    "sourceId": "source8",
                    "fact": "Chile"
                },
                {
                    "sourceId": "source9",
                    "fact": "Sri Lanka"
                },
                {
                    "sourceId": "source10",
                    "fact": "Azerbaijan"
                }
            ]
        }
    ],
    "sources": []
}