{
    "timestamp": "2025-09-17T16:18:08.949338",
    "objects": [
        {
            "name": "name",
            "claims": [
                {
                    "fact": "Samantha Kemp Valenzuela Villegas",
                    "confidence": 0.676,
                    "sourceId": "source10"
                },
                {
                    "fact": "Samantha Kemp Valenzuela Villegas",
                    "confidence": 0.676,
                    "sourceId": "source14"
                },
                {
                    "fact": "Santha Kemp Valenzela Villegas",
                    "confidence": 0.671,
                    "sourceId": "source7"
                },
                {
                    "fact": "Melissa Kemp Valenzuela Villegas",
                    "confidence": 0.647,
                    "sourceId": "source9"
                },
                {
                    "fact": "Patricia Smith Morales",
                    "confidence": 0.574,
                    "sourceId": "source3"
                }
            ]
        }
    ],
    "sources": [
        {
            "sourceId": "source3",
            "reputation": 0.5,
            "probabilities": [
                0.1,
                0.1,
                0.6,
                0.1,
                0.1
            ],
            "ratings": [
                0,
                0,
                5,
                0,
                0
            ]
        },
        {
            "sourceId": "source9",
            "reputation": 0.5555555555555556,
            "probabilities": [
                0.1111111111111111,
                0.1111111111111111,
                0.3333333333333333,
                0.3333333333333333,
                0.1111111111111111
            ],
            "ratings": [
                0,
                0,
                2,
                2,
                0
            ]
        },
        {
            "sourceId": "source10",
            "reputation": 0.5625,
            "probabilities": [
                0.125,
                0.125,
                0.25,
                0.375,
                0.125
            ],
            "ratings": [
                0,
                0,
                1,
                2,
                0
            ]
        },
        {
            "sourceId": "source7",
            "reputation": 0.5714285714285714,
            "probabilities": [
                0.14285714285714285,
                0.14285714285714285,
                0.14285714285714285,
                0.42857142857142855,
                0.14285714285714285
            ],
            "ratings": [
                0,
                0,
                0,
                2,
                0
            ]
        },
        {
            "sourceId": "source14",
            "reputation": 0.5416666666666666,
            "probabilities": [
                0.16666666666666666,
                0.16666666666666666,
                0.16666666666666666,
                0.3333333333333333,
                0.16666666666666666
            ],
            "ratings": [
                0,
                0,
                0,
                1,
                0
            ]
        }
    ]
}