{
    "timestamp": "2025-09-17T16:15:45.541552",
    "objects": [
        {
            "name": "nationality",
            "claims": [
                {
                    "fact": "Malta",
                    "confidence": 0.874,
                    "sourceId": "source7"
                },
                {
                    "fact": "Malta",
                    "confidence": 0.874,
                    "sourceId": "source3"
                },
                {
                    "fact": "Malta",
                    "confidence": 0.874,
                    "sourceId": "source10"
                }
            ]
        },
        {
            "name": "name",
            "claims": [
                {
                    "fact": "Erin Flynn Dixon Shannon",
                    "confidence": 0.868,
                    "sourceId": "source5"
                },
                {
                    "fact": "Erin Flynn Dixon Shannon",
                    "confidence": 0.868,
                    "sourceId": "source3"
                },
                {
                    "fact": "Erin Flynn Dixon Shannon",
                    "confidence": 0.868,
                    "sourceId": "source7"
                }
            ]
        },
        {
            "name": "age",
            "claims": [
                {
                    "fact": 33.0,
                    "confidence": 0.824,
                    "sourceId": "source3"
                },
                {
                    "fact": 33.0,
                    "confidence": 0.824,
                    "sourceId": "source5"
                },
                {
                    "fact": 31.0,
                    "confidence": 0.808,
                    "sourceId": "source2"
                }
            ]
        }
    ],
    "sources": [
        {
            "sourceId": "source10",
            "reputation": 0.8970588235294117,
            "probabilities": [
                0.029411764705882353,
                0.029411764705882353,
                0.029411764705882353,
                0.14705882352941177,
                0.7647058823529411
            ],
            "ratings": [
                0,
                0,
                0,
                4,
                25
            ]
        },
        {
            "sourceId": "source7",
            "reputation": 0.8898305084745762,
            "probabilities": [
                0.01694915254237288,
                0.01694915254237288,
                0.03389830508474576,
                0.2542372881355932,
                0.6779661016949152
            ],
            "ratings": [
                0,
                0,
                1,
                14,
                39
            ]
        },
        {
            "sourceId": "source3",
            "reputation": 0.875,
            "probabilities": [
                0.014705882352941176,
                0.014705882352941176,
                0.029411764705882353,
                0.3382352941176471,
                0.6029411764705882
            ],
            "ratings": [
                0,
                0,
                1,
                22,
                40
            ]
        },
        {
            "sourceId": "source5",
            "reputation": 0.875,
            "probabilities": [
                0.018518518518518517,
                0.018518518518518517,
                0.037037037037037035,
                0.2962962962962963,
                0.6296296296296297
            ],
            "ratings": [
                0,
                0,
                1,
                15,
                33
            ]
        },
        {
            "sourceId": "source2",
            "reputation": 0.6964285714285714,
            "probabilities": [
                0.17857142857142858,
                0.03571428571428571,
                0.10714285714285714,
                0.17857142857142858,
                0.5
            ],
            "ratings": [
                4,
                0,
                2,
                4,
                13
            ]
        }
    ]
}