{
    "timestamp": "2025-09-17T16:17:07.140660",
    "objects": [
        {
            "name": "nationality",
            "claims": [
                {
                    "fact": "Slovakia (Slovak Republic)",
                    "confidence": 0.122,
                    "sourceId": "source20"
                },
                {
                    "fact": "Slovakia (Slovak Republic)",
                    "confidence": 0.122,
                    "sourceId": "source17"
                },
                {
                    "fact": "Slovakia (Slovak Republic)",
                    "confidence": 0.122,
                    "sourceId": "source19"
                },
                {
                    "fact": "Russian Federation",
                    "confidence": 0.042,
                    "sourceId": "source5"
                },
                {
                    "fact": "South Georgia and the South Sandwich Islands",
                    "confidence": 0.039,
                    "sourceId": "source6"
                },
                {
                    "fact": "Liechtenstein",
                    "confidence": 0.038,
                    "sourceId": "source14"
                },
                {
                    "fact": "United States Minor Outlying Islands",
                    "confidence": 0.037,
                    "sourceId": "source4"
                },
                {
                    "fact": "Uzbekistan",
                    "confidence": 0.036,
                    "sourceId": "source2"
                },
                {
                    "fact": "Netherlands Antilles",
                    "confidence": 0.036,
                    "sourceId": "source9"
                },
                {
                    "fact": "Lebanon",
                    "confidence": 0.035,
                    "sourceId": "source7"
                },
                {
                    "fact": "Congo",
                    "confidence": 0.034,
                    "sourceId": "source8"
                },
                {
                    "fact": "Seychelles",
                    "confidence": 0.033,
                    "sourceId": "source12"
                },
                {
                    "fact": "Guam",
                    "confidence": 0.029,
                    "sourceId": "source11"
                },
                {
                    "fact": "Marshall Islands",
                    "confidence": 0.028,
                    "sourceId": "source3"
                },
                {
                    "fact": "Ghana",
                    "confidence": 0.028,
                    "sourceId": "source15"
                }
            ]
        },
        {
            "name": "name",
            "claims": [
                {
                    "fact": "Patricia Chavez Todd",
                    "confidence": 0.98,
                    "sourceId": "source19"
                },
                {
                    "fact": "Patricia Chavez Todd",
                    "confidence": 0.98,
                    "sourceId": "source17"
                },
                {
                    "fact": "Patricia Chavez Todd",
                    "confidence": 0.98,
                    "sourceId": "source20"
                },
                {
                    "fact": "Patricia havz Tdd",
                    "confidence": 0.976,
                    "sourceId": "source6"
                },
                {
                    "fact": "Patricic Chave Todd",
                    "confidence": 0.974,
                    "sourceId": "source14"
                },
                {
                    "fact": "Patricia Cavez ody",
                    "confidence": 0.972,
                    "sourceId": "source7"
                },
                {
                    "fact": "Patricia Maria Todd",
                    "confidence": 0.969,
                    "sourceId": "source10"
                },
                {
                    "fact": "Patricia Leslie Todd",
                    "confidence": 0.967,
                    "sourceId": "source13"
                },
                {
                    "fact": "Patricia John Todd",
                    "confidence": 0.965,
                    "sourceId": "source16"
                },
                {
                    "fact": "ParDcia Chavez Todd",
                    "confidence": 0.964,
                    "sourceId": "source4"
                },
                {
                    "fact": "Patricia Chavez Garrett",
                    "confidence": 0.94,
                    "sourceId": "source8"
                },
                {
                    "fact": "Katherine Chavez Todd",
                    "confidence": 0.906,
                    "sourceId": "source1"
                },
                {
                    "fact": "Richard Chavez Todd",
                    "confidence": 0.905,
                    "sourceId": "source2"
                },
                {
                    "fact": "Matthew Cooper Rangel Gonzales",
                    "confidence": 0.572,
                    "sourceId": "source15"
                },
                {
                    "fact": "Lisa Brown Brown Hess",
                    "confidence": 0.396,
                    "sourceId": "source3"
                }
            ]
        },
        {
            "name": "age",
            "claims": [
                {
                    "fact": 30.0,
                    "confidence": 0.991,
                    "sourceId": "source18"
                },
                {
                    "fact": 30.0,
                    "confidence": 0.991,
                    "sourceId": "source19"
                },
                {
                    "fact": 30.0,
                    "confidence": 0.991,
                    "sourceId": "source20"
                },
                {
                    "fact": 29.0,
                    "confidence": 0.991,
                    "sourceId": "source7"
                },
                {
                    "fact": 29.0,
                    "confidence": 0.991,
                    "sourceId": "source4"
                },
                {
                    "fact": 28.0,
                    "confidence": 0.99,
                    "sourceId": "source10"
                },
                {
                    "fact": 31.0,
                    "confidence": 0.99,
                    "sourceId": "source9"
                },
                {
                    "fact": 32.0,
                    "confidence": 0.988,
                    "sourceId": "source5"
                },
                {
                    "fact": 32.0,
                    "confidence": 0.988,
                    "sourceId": "source14"
                },
                {
                    "fact": 32.0,
                    "confidence": 0.988,
                    "sourceId": "source6"
                },
                {
                    "fact": 26.0,
                    "confidence": 0.986,
                    "sourceId": "source16"
                },
                {
                    "fact": 33.0,
                    "confidence": 0.985,
                    "sourceId": "source12"
                },
                {
                    "fact": 25.0,
                    "confidence": 0.982,
                    "sourceId": "source13"
                },
                {
                    "fact": 25.0,
                    "confidence": 0.982,
                    "sourceId": "source2"
                },
                {
                    "fact": 34.0,
                    "confidence": 0.98,
                    "sourceId": "source11"
                }
            ]
        }
    ],
    "sources": [
        {
            "sourceId": "source15",
            "reputation": 0.3653846153846154,
            "probabilities": [
                0.29914529914529914,
                0.1111111111111111,
                0.49572649572649574,
                0.017094017094017096,
                0.07692307692307693
            ],
            "ratings": [
                34,
                12,
                57,
                1,
                8
            ]
        },
        {
            "sourceId": "source1",
            "reputation": 0.7581967213114754,
            "probabilities": [
                0.14754098360655737,
                0.01639344262295082,
                0.01639344262295082,
                0.29508196721311475,
                0.5245901639344263
            ],
            "ratings": [
                8,
                0,
                0,
                17,
                31
            ]
        },
        {
            "sourceId": "source8",
            "reputation": 0.538235294117647,
            "probabilities": [
                0.38823529411764707,
                0.07058823529411765,
                0.011764705882352941,
                0.058823529411764705,
                0.47058823529411764
            ],
            "ratings": [
                32,
                5,
                0,
                4,
                39
            ]
        },
        {
            "sourceId": "source17",
            "reputation": 0.6230769230769231,
            "probabilities": [
                0.35384615384615387,
                0.015384615384615385,
                0.015384615384615385,
                0.015384615384615385,
                0.6
            ],
            "ratings": [
                22,
                0,
                0,
                0,
                38
            ]
        },
        {
            "sourceId": "source3",
            "reputation": 0.3670212765957447,
            "probabilities": [
                0.2978723404255319,
                0.1702127659574468,
                0.40425531914893614,
                0.02127659574468085,
                0.10638297872340426
            ],
            "ratings": [
                13,
                7,
                18,
                0,
                4
            ]
        },
        {
            "sourceId": "source5",
            "reputation": 0.6851851851851852,
            "probabilities": [
                0.24691358024691357,
                0.012345679012345678,
                0.04938271604938271,
                0.13580246913580246,
                0.5555555555555556
            ],
            "ratings": [
                19,
                0,
                3,
                10,
                44
            ]
        },
        {
            "sourceId": "source14",
            "reputation": 0.6238938053097345,
            "probabilities": [
                0.2743362831858407,
                0.09734513274336283,
                0.008849557522123894,
                0.09734513274336283,
                0.5221238938053098
            ],
            "ratings": [
                30,
                10,
                0,
                10,
                58
            ]
        },
        {
            "sourceId": "source10",
            "reputation": 0.9081632653061225,
            "probabilities": [
                0.05102040816326531,
                0.01020408163265306,
                0.01020408163265306,
                0.11224489795918367,
                0.8163265306122449
            ],
            "ratings": [
                4,
                0,
                0,
                10,
                79
            ]
        },
        {
            "sourceId": "source13",
            "reputation": 0.8660714285714286,
            "probabilities": [
                0.0625,
                0.008928571428571428,
                0.03571428571428571,
                0.1875,
                0.7053571428571429
            ],
            "ratings": [
                6,
                0,
                3,
                20,
                78
            ]
        },
        {
            "sourceId": "source18",
            "reputation": 0.9107142857142857,
            "probabilities": [
                0.05357142857142857,
                0.017857142857142856,
                0.017857142857142856,
                0.05357142857142857,
                0.8571428571428571
            ],
            "ratings": [
                2,
                0,
                0,
                2,
                47
            ]
        },
        {
            "sourceId": "source6",
            "reputation": 0.6372950819672131,
            "probabilities": [
                0.2540983606557377,
                0.12295081967213115,
                0.02459016393442623,
                0.01639344262295082,
                0.5819672131147541
            ],
            "ratings": [
                30,
                14,
                2,
                1,
                70
            ]
        },
        {
            "sourceId": "source9",
            "reputation": 0.5878378378378378,
            "probabilities": [
                0.3918918918918919,
                0.013513513513513514,
                0.013513513513513514,
                0.013513513513513514,
                0.5675675675675675
            ],
            "ratings": [
                28,
                0,
                0,
                0,
                41
            ]
        },
        {
            "sourceId": "source12",
            "reputation": 0.527027027027027,
            "probabilities": [
                0.35135135135135137,
                0.14864864864864866,
                0.013513513513513514,
                0.013513513513513514,
                0.47297297297297297
            ],
            "ratings": [
                25,
                10,
                0,
                0,
                34
            ]
        },
        {
            "sourceId": "source7",
            "reputation": 0.5636363636363636,
            "probabilities": [
                0.3,
                0.13636363636363635,
                0.06363636363636363,
                0.00909090909090909,
                0.4909090909090909
            ],
            "ratings": [
                32,
                14,
                6,
                0,
                53
            ]
        },
        {
            "sourceId": "source2",
            "reputation": 0.5963855421686747,
            "probabilities": [
                0.3855421686746988,
                0.012048192771084338,
                0.012048192771084338,
                0.012048192771084338,
                0.5783132530120482
            ],
            "ratings": [
                31,
                0,
                0,
                0,
                47
            ]
        },
        {
            "sourceId": "source19",
            "reputation": 0.7780898876404494,
            "probabilities": [
                0.19101123595505617,
                0.011235955056179775,
                0.011235955056179775,
                0.06741573033707865,
                0.7191011235955056
            ],
            "ratings": [
                16,
                0,
                0,
                5,
                63
            ]
        },
        {
            "sourceId": "source4",
            "reputation": 0.60546875,
            "probabilities": [
                0.25,
                0.125,
                0.046875,
                0.109375,
                0.46875
            ],
            "ratings": [
                31,
                15,
                5,
                13,
                59
            ]
        },
        {
            "sourceId": "source11",
            "reputation": 0.4,
            "probabilities": [
                0.4533333333333333,
                0.14666666666666667,
                0.013333333333333334,
                0.12,
                0.26666666666666666
            ],
            "ratings": [
                33,
                10,
                0,
                8,
                19
            ]
        },
        {
            "sourceId": "source16",
            "reputation": 0.8038461538461539,
            "probabilities": [
                0.16923076923076924,
                0.015384615384615385,
                0.015384615384615385,
                0.03076923076923077,
                0.7692307692307693
            ],
            "ratings": [
                10,
                0,
                0,
                1,
                49
            ]
        },
        {
            "sourceId": "source20",
            "reputation": 0.44230769230769235,
            "probabilities": [
                0.5230769230769231,
                0.03076923076923077,
                0.015384615384615385,
                0.015384615384615385,
                0.4153846153846154
            ],
            "ratings": [
                33,
                1,
                0,
                0,
                26
            ]
        }
    ]
}